django_dartium/__init__.py
django_dartium/middleware.py
django_dartium/templatetags/__init__.py
django_dartium/templatetags/dartium.py
django_dartium-0.1.3.dist-info/DESCRIPTION.rst
django_dartium-0.1.3.dist-info/METADATA
django_dartium-0.1.3.dist-info/RECORD
django_dartium-0.1.3.dist-info/WHEEL
django_dartium-0.1.3.dist-info/metadata.json
django_dartium-0.1.3.dist-info/top_level.txt
