Metadata-Version: 2.0
Name: django-dartium
Version: 0.1.3
Summary: Django Middlware to detect Dartium web browser.
Home-page: https://github.com/damoti/django-dartium
Author: Lex Berezhny
Author-email: lex@damoti.com
License: MIT
Keywords: django,dart,dartium
Platform: UNKNOWN
Classifier: Framework :: Django
Classifier: Intended Audience :: Developers
Classifier: License :: OSI Approved :: MIT License
Classifier: Programming Language :: Python :: 3
Classifier: Operating System :: OS Independent
Classifier: Topic :: Software Development :: Libraries :: Python Modules
Classifier: Topic :: Software Development :: Testing
Classifier: Topic :: Software Development :: User Interfaces
